fastapi_testdb/__init__.py
fastapi_testdb/testdb.py
fastapi_testdb-0.1.2.dist-info/LICENSE
fastapi_testdb-0.1.2.dist-info/METADATA
fastapi_testdb-0.1.2.dist-info/WHEEL
fastapi_testdb-0.1.2.dist-info/top_level.txt
fastapi_testdb-0.1.2.dist-info/RECORD
