Metadata-Version: 2.1
Name: fastapi-testdb
Version: 0.1.2
Summary: Reproducible SQL database state for testing routines
Author-email: Dmitrii Kononenko <dmitriy.sergeevitch@gmail.com>
License: MIT License
Project-URL: repository, https://github.com/Dmitry-k42/fastapi_testdb
Keywords: FastAPI,testing,SQLAlchemy,database,pytest
Classifier: License :: OSI Approved :: MIT License
Classifier: Programming Language :: Python
Classifier: Programming Language :: Python :: 3
Requires-Python: >=3.7
License-File: LICENSE
Requires-Dist: fastapi (>=0.91.0)
Requires-Dist: SQLAlchemy (>=2.0.3)
Provides-Extra: dev
Requires-Dist: pytest ; extra == 'dev'
Requires-Dist: httpx ; extra == 'dev'
Requires-Dist: pylint ; extra == 'dev'
Requires-Dist: build ; extra == 'dev'
Requires-Dist: twine ; extra == 'dev'
